mojo/rpc/__init__.py
mojo/rpc/core/__init__.py
mojo/rpc/core/duplexclientsession.py
mojo/rpc/core/duplexserversession.py
mojo/rpc/core/duplexsocketio.py
mojo/rpc/core/flattenable.py
mojo/rpc/core/looper.py
mojo/rpc/core/looperpool.py
mojo/rpc/core/looperqueue.py
mojo/rpc/core/objectref.py
mojo/rpc/core/protocol.py
mojo/rpc/core/proxy.py
mojo/rpc/rpcsocketclient.py
mojo/rpc/rpcsocketserver.py
mojo_rpc-0.0.3.dist-info/LICENSE.txt
mojo_rpc-0.0.3.dist-info/METADATA
mojo_rpc-0.0.3.dist-info/WHEEL
mojo_rpc-0.0.3.dist-info/RECORD
