Metadata-Version: 2.1
Name: mojo-rpc
Version: 0.0.3
Summary: Automation Mojo - RPC
License: LICENSE.txt
Keywords: python
Requires-Python: >=3.9,<4.0
Classifier: License :: OSI Approved :: MIT License
Classifier: License :: Other/Proprietary License
Classifier: Operating System :: POSIX
Classifier: Programming Language :: Python :: 3
Classifier: Programming Language :: Python :: 3.9
Classifier: Programming Language :: Python :: 3.10
Classifier: Programming Language :: Python :: 3.11
Classifier: Programming Language :: Python :: 3.12
Requires-Dist: mojo-errors (>=1.3.8,<2.0.0)
